MANIFEST.in
README.rst
pytest.ini
setup.cfg
setup.py
horus/__init__.py
horus/exceptions.py
horus/forms.py
horus/horus_demo.py
horus/httpexceptions.py
horus/interfaces.py
horus/lib.py
horus/models.py
horus/resources.py
horus/routes.py
horus/schemas.py
horus/strings.py
horus.egg-info/PKG-INFO
horus.egg-info/SOURCES.txt
horus.egg-info/dependency_links.txt
horus.egg-info/entry_points.txt
horus.egg-info/not-zip-safe
horus.egg-info/requires.txt
horus.egg-info/top_level.txt
horus/events/__init__.py
horus/scripts/__init__.py
horus/scripts/scaffold.py
horus/static/assets/css/bootstrap-responsive.css
horus/static/assets/css/bootstrap-responsive.min.css
horus/static/assets/css/bootstrap.css
horus/static/assets/css/bootstrap.min.css
horus/static/assets/img/glyphicons-halflings-white.png
horus/static/assets/img/glyphicons-halflings.png
horus/static/assets/js/bootstrap.js
horus/static/assets/js/bootstrap.min.js
horus/static/assets/js/jquery.js
horus/templates/edit_profile.mako
horus/templates/forgot_password.mako
horus/templates/layout.mako
horus/templates/login.mako
horus/templates/profile.mako
horus/templates/register.mako
horus/templates/reset_password.mako
horus/templates/admin/create_user.mako
horus/templates/admin/index.mako
horus/templates/admin/users_index.mako
horus/tests/__init__.py
horus/tests/models.py
horus/tests/schemas.py
horus/tests/test.ini
horus/tests/test_init.py
horus/tests/test_integration.py
horus/tests/test_interfaces.py
horus/tests/test_models.py
horus/tests/test_resources.py
horus/tests/test_schemas.py
horus/tests/test_views.py
horus/views/__init__.py
horus/views/admin.py