Metadata-Version: 1.1
Name: horus
Version: 0.9.15
Summary: Generic user registration for pyramid
Home-page: https://github.com/eventray/horus
Author: John Anderson
Author-email: sontek@gmail.com
License: BSD
Keywords: pyramid,authentication,user registration
Platform: UNKNOWN
Classifier: Development Status :: 5 - Production/Stable
Classifier: Intended Audience :: Developers
Classifier: License :: OSI Approved :: BSD License
Classifier: Operating System :: OS Independent
Classifier: Programming Language :: Python
Classifier: Programming Language :: Python :: 2
Classifier: Programming Language :: Python :: 2.7
Classifier: Programming Language :: Python :: 3
Classifier: Programming Language :: Python :: 3.3
Classifier: Topic :: Internet :: WWW/HTTP :: Dynamic Content
Classifier: Topic :: Software Development :: Libraries :: Python Modules
